shedding/__init__.py
shedding/_http.py
shedding/allowance.py
shedding/area.py
shedding/status.py
shedding/topics.py
shedding/types/__init__.py
shedding/types/allowance.py
shedding/types/area.py
shedding/types/status.py
shedding/types/topics.py
shedding_py-1.0.0.dist-info/LICENSE
shedding_py-1.0.0.dist-info/METADATA
shedding_py-1.0.0.dist-info/WHEEL
shedding_py-1.0.0.dist-info/RECORD
